MANIFEST.in
README.md
requirements.txt
setup.cfg
setup.py
slavem/__init__.py
slavem/constant.py
slavem/emails.py
slavem/monitor.py
slavem/reporter.py
slavem/tasks.py
slavem.egg-info/PKG-INFO
slavem.egg-info/SOURCES.txt
slavem.egg-info/dependency_links.txt
slavem.egg-info/requires.txt
slavem.egg-info/top_level.txt