Metadata-Version: 1.1
Name: slavem
Version: 0.3.4
Summary: 监控全网服务的服务 2018.03.26
Home-page: https://github.com/lamter/slavem
Author: lamter
Author-email: lamter.fu@gmail.com
License: UNKNOWN
Keywords: slavem
Platform: UNKNOWN
Classifier: Programming Language :: Python :: 2.7
Classifier: Programming Language :: Python :: 3.5
Classifier: Programming Language :: Python :: 3.6
Classifier: License :: OSI Approved :: MIT License
